geopephub/__init__.py
geopephub/__version__.py
geopephub/bedbase_stats.py
geopephub/bunch_geo.py
geopephub/cli.py
geopephub/const.py
geopephub/db_utils.py
geopephub/main.py
geopephub/metageo_pephub.py
geopephub/models.py
geopephub/utils.py
geopephub-0.1.0.dist-info/LICENSE.txt
geopephub-0.1.0.dist-info/METADATA
geopephub-0.1.0.dist-info/WHEEL
geopephub-0.1.0.dist-info/entry_points.txt
geopephub-0.1.0.dist-info/RECORD
