Metadata-Version: 2.1
Name: geopephub
Version: 0.1.0
Summary: Pipeline for processing GEO data and uploading it to the PEPHub
Home-page: https://github.com/pepkit/geoephub
License: BSD-2-Clause license
Author: Oleksandr Khoroshevskyi
Author-email: khorosh@virginia.edu
Requires-Python: >=3.8,<4.0
Classifier: Development Status :: 4 - Beta
Classifier: License :: OSI Approved :: BSD License
Classifier: License :: Other/Proprietary License
Classifier: Programming Language :: Python :: 3
Classifier: Programming Language :: Python :: 3.8
Classifier: Programming Language :: Python :: 3.9
Classifier: Programming Language :: Python :: 3.10
Classifier: Programming Language :: Python :: 3.11
Classifier: Programming Language :: Python :: 3.12
Classifier: Programming Language :: Python :: 3 :: Only
Classifier: Topic :: Database
Requires-Dist: SQLAlchemy (>=2.0.0,<2.1.0)
Requires-Dist: boto3 (>=1.34.29,<2.0.0)
Requires-Dist: botocore (>=1.34.29,<2.0.0)
Requires-Dist: coloredlogs (>=15.0.1,<16.0.0)
Requires-Dist: geofetch (>=0.12.7,<0.13.0)
Requires-Dist: hypothesis (>=6.112.0,<7.0.0)
Requires-Dist: logmuse (>=0.2.7,<0.3.0)
Requires-Dist: pepdbagent (>=0.11.1,<0.12.0)
Requires-Dist: pephubclient (>=0.4.4,<0.5.0)
Requires-Dist: peppy (>=0.40.7,<0.41.0)
Requires-Dist: pydantic (>=2.5.0,<3.0.0)
Requires-Dist: python-dotenv (>=1.0.1,<2.0.0)
Requires-Dist: typer (>=0.9.0,<0.10.0)
Project-URL: Documentation, https://github.com/pepkit/geoephub
Project-URL: Repository, https://github.com/pepkit/geoephub
